setup.py
otis/__init__.py
otis/pandas.py
otis_pandas.egg-info/PKG-INFO
otis_pandas.egg-info/SOURCES.txt
otis_pandas.egg-info/dependency_links.txt
otis_pandas.egg-info/requires.txt
otis_pandas.egg-info/top_level.txt