Metadata-Version: 1.0
Name: otis-pandas
Version: 0.0.1
Summary: Open Timeseries Interface Service pandas bindings
Home-page: https://github.com/hodgesds/otis-pandas
Author: Daniel Hodges
Author-email: hodges.daniel.scott@gmail.com
License: UNKNOWN
Platform: UNKNOWN
